juju_vnfm-1.0.0b23.data/scripts/jujuvnfm
juju_vnfm-1.0.0b23.dist-info/DESCRIPTION.rst
juju_vnfm-1.0.0b23.dist-info/METADATA
juju_vnfm-1.0.0b23.dist-info/RECORD
juju_vnfm-1.0.0b23.dist-info/WHEEL
juju_vnfm-1.0.0b23.dist-info/metadata.json
juju_vnfm-1.0.0b23.dist-info/top_level.txt
jujuvnfm/__init__.py
jujuvnfm/juju_helper.py
jujuvnfm/juju_new_helper.py
jujuvnfm/juju_vnfm.py
jujuvnfm/juju_waiter.py
jujuvnfm/waiter_exceptions.py
jujuvnfm/etc/icon.svg
tests/__init__.py
tests/asyncio_test.py
tests/juju_tests.py
utils/__init__.py
utils/utils.py
