Metadata-Version: 2.0
Name: juju-vnfm
Version: 1.0.0b23
Summary: The Python version of a Juju Vnfm for Open Baton
Home-page: http://openbaton.github.io/
Author: Open Baton Team
Author-email: dev@openbaton.org
License: Apache 2
Keywords: python vnfm nfvo open baton openbaton sdk juju
Platform: UNKNOWN
Classifier: Development Status :: 4 - Beta
Classifier: Programming Language :: Python :: 3.5
Classifier: Intended Audience :: Developers
Classifier: Topic :: Software Development :: Build Tools
Classifier: Topic :: Utilities
Classifier: License :: OSI Approved :: Apache Software License
Requires-Dist: configparser
Requires-Dist: jujuclient (==0.53.3)
Requires-Dist: python-vnfm-sdk (==3.2.0b7)
